orgnb.py
orgnb-0.2.0.dist-info/LICENSE
orgnb-0.2.0.dist-info/METADATA
orgnb-0.2.0.dist-info/WHEEL
orgnb-0.2.0.dist-info/entry_points.txt
orgnb-0.2.0.dist-info/top_level.txt
orgnb-0.2.0.dist-info/RECORD
