Metadata-Version: 2.2
Name: orgnb
Version: 0.2.0
Summary: Convert org-mode files to jupyter notebooks
Author-email: Daniele Coslovich <dcoslovich@umontpellier.fr>
License: GPLv3
Project-URL: repository, https://framagit.org/coslo/orgnb
Classifier: License :: OSI Approved :: GNU General Public License v3 (GPLv3)
Classifier: Programming Language :: Python :: 3
Classifier: Development Status :: 5 - Production/Stable
Requires-Python: >=3.6
License-File: LICENSE
Requires-Dist: pypandoc_binary
Requires-Dist: nbformat
Requires-Dist: argh
